LICENSE
MANIFEST.in
README.rst
setup.py
mecan4cna/__init__.py
mecan4cna/algorithms.py
mecan4cna/cli.py
mecan4cna/common.py
mecan4cna/detect_peaks.py
mecan4cna/run_mecan_example.sh
mecan4cna.egg-info/PKG-INFO
mecan4cna.egg-info/SOURCES.txt
mecan4cna.egg-info/dependency_links.txt
mecan4cna.egg-info/entry_points.txt
mecan4cna.egg-info/requires.txt
mecan4cna.egg-info/top_level.txt
mecan4cna/examples/.DS_Store
mecan4cna/examples/segment_example_1.tsv
mecan4cna/examples/segment_example_2.tsv
mecan4cna/examples/segment_example_3.tsv
mecan4cna/examples/segment_example_4.tsv
mecan4cna/examples/segment_example_5.tsv